nonebot_plugin_poke-0.1.6.dist-info/METADATA
nonebot_plugin_poke-0.1.6.dist-info/WHEEL
nonebot_plugin_poke-0.1.6.dist-info/entry_points.txt
nonebot_plugin_poke-0.1.6.dist-info/licenses/LICENSE
nonebot_plugin_poke/__init__.py
nonebot_plugin_poke/config.py
nonebot_plugin_poke/matcher.py
nonebot_plugin_poke/utils.py
nonebot_plugin_poke-0.1.6.dist-info/RECORD
