Metadata-Version: 2.1
Name: nonebot_plugin_poke
Version: 0.1.6
Summary: 自定义群聊戳戳事件 plugin for NoneBot2
Keywords: nonebot2,plugin,poke
Author-Email: Agnes_Digital <Z735803792@163.com>
License: MIT
Classifier: License :: OSI Approved :: MIT License
Classifier: Programming Language :: Python
Classifier: Programming Language :: Python :: 3
Classifier: Programming Language :: Python :: 3.9
Classifier: Programming Language :: Python :: 3.10
Classifier: Programming Language :: Python :: 3.11
Classifier: Programming Language :: Python :: 3.12
Classifier: Programming Language :: Python :: 3.13
Classifier: Operating System :: OS Independent
Requires-Python: <4.0,>=3.9
Requires-Dist: nonebot2>=2.1.0
Requires-Dist: nonebot-plugin-alconna>=0.58.5
Requires-Dist: nonebot-adapter-onebot>=2.1.5
Requires-Dist: aiofiles>=23.1.0
Requires-Dist: aiohttp>=3.8.5
Requires-Dist: pydantic>=2.1.1
